pysqrtrootof3taker/__init__.py
pysqrtrootof3taker/pysqrtrootof3taker.py
pysqrtrootof3taker-1.0.0.dist-info/LICENSE
pysqrtrootof3taker-1.0.0.dist-info/METADATA
pysqrtrootof3taker-1.0.0.dist-info/WHEEL
pysqrtrootof3taker-1.0.0.dist-info/top_level.txt
pysqrtrootof3taker-1.0.0.dist-info/RECORD
