Metadata-Version: 2.1
Name: pysqrtrootof3taker
Version: 1.0.0
Summary: For computing the square root of 3 fastly and securely in a local environment.
Home-page: https://github.com/TheCoderLab/pysqrtrootof3taker
Author: Rudra Singh Rathore
Author-email: rudrasinghrathore16022012@gmail.com
Classifier: Programming Language :: Python :: 3
Classifier: License :: OSI Approved :: MIT License
Classifier: Operating System :: OS Independent
Requires-Python: >=3.7
License-File: LICENSE
